syntha/__init__.py
syntha/context.py
syntha/exceptions.py
syntha/framework_adapters.py
syntha/logging.py
syntha/persistence.py
syntha/prompts.py
syntha/reports.py
syntha/tool_factory.py
syntha/tools.py
syntha-0.2.7.dist-info/licenses/LICENSE
syntha-0.2.7.dist-info/licenses/NOTICE
syntha-0.2.7.dist-info/METADATA
syntha-0.2.7.dist-info/WHEEL
syntha-0.2.7.dist-info/top_level.txt
syntha-0.2.7.dist-info/RECORD
