Metadata-Version: 2.4
Name: syntha
Version: 0.2.7
Summary: Prompt-based multi-agent context framework
Home-page: https://github.com/syntha/syntha-sdk
Author: Syntha Team
Author-email: Syntha Team <contact@syntha.ai>
License: Apache-2.0
Project-URL: Homepage, https://github.com/Kirch77/syntha
Project-URL: Repository, https://github.com/Kirch77/syntha
Project-URL: Documentation, https://doc.syntha.ca
Project-URL: Issues, https://github.com/Kirch77/syntha/issues
Classifier: Development Status :: 3 - Alpha
Classifier: Intended Audience :: Developers
Classifier: License :: OSI Approved :: Apache Software License
Classifier: Operating System :: OS Independent
Classifier: Programming Language :: Python :: 3
Classifier: Programming Language :: Python :: 3.9
Classifier: Programming Language :: Python :: 3.10
Classifier: Programming Language :: Python :: 3.11
Requires-Python: >=3.9
License-File: LICENSE
License-File: NOTICE
Requires-Dist: typing-extensions>=4.0.0
Provides-Extra: dev
Requires-Dist: pytest>=7.0.0; extra == "dev"
Requires-Dist: black>=22.0.0; extra == "dev"
Requires-Dist: isort>=5.0.0; extra == "dev"
Requires-Dist: mypy>=1.0.0; extra == "dev"
Provides-Extra: frameworks
Requires-Dist: langchain>=0.1.0; extra == "frameworks"
Requires-Dist: langgraph>=0.1.0; extra == "frameworks"
Requires-Dist: openai>=1.0.0; extra == "frameworks"
Requires-Dist: anthropic>=0.25.0; extra == "frameworks"
Requires-Dist: agno>=1.0.0; extra == "frameworks"
Dynamic: author
Dynamic: home-page
Dynamic: license-file
Dynamic: requires-python
